{
	"configurations" : 
	[
		{
			"directories" : 
			[
				{
					"build" : ".",
					"childIndexes" : 
					[
						1
					],
					"jsonFile" : "directory-.-Debug-d0094a50bb2071803777.json",
					"minimumCMakeVersion" : 
					{
						"string" : "3.23"
					},
					"projectIndex" : 0,
					"source" : ".",
					"targetIndexes" : 
					[
						0
					]
				},
				{
					"build" : "test",
					"jsonFile" : "directory-test-Debug-f18be1977b403cfd1a50.json",
					"minimumCMakeVersion" : 
					{
						"string" : "3.23"
					},
					"parentIndex" : 0,
					"projectIndex" : 0,
					"source" : "test",
					"targetIndexes" : 
					[
						1
					]
				}
			],
			"name" : "Debug",
			"projects" : 
			[
				{
					"directoryIndexes" : 
					[
						0,
						1
					],
					"name" : "bioloog",
					"targetIndexes" : 
					[
						0,
						1
					]
				}
			],
			"targets" : 
			[
				{
					"directoryIndex" : 0,
					"id" : "bioloog::@6890427a1f51a3e7e1df",
					"jsonFile" : "target-bioloog-Debug-98a637982e8b3bd8d716.json",
					"name" : "bioloog",
					"projectIndex" : 0
				},
				{
					"directoryIndex" : 1,
					"id" : "test::@36f028580bb02cc8272a",
					"jsonFile" : "target-test-Debug-4df02d5bd1e119e54648.json",
					"name" : "test",
					"projectIndex" : 0
				}
			]
		}
	],
	"kind" : "codemodel",
	"paths" : 
	{
		"build" : "C:/Users/Stefano/source/repos/bioloog/cmake-build-debug",
		"source" : "C:/Users/Stefano/source/repos/bioloog"
	},
	"version" : 
	{
		"major" : 2,
		"minor" : 4
	}
}
